projection/__init__.py
projection/elements/__init__.py
projection/elements/base.py
projection/elements/div.py
projection/externals/__init__.py
projection/externals/stdout.py
projection/static/css/main.css
projection/static/index.html
projection/static/js/elements.js
projection/static/js/main.js
projection/static/js/stores.js
projection_ui-0.0.0.20210227.dist-info/WHEEL
projection_ui-0.0.0.20210227.dist-info/METADATA
projection_ui-0.0.0.20210227.dist-info/RECORD
